passbird/__init__.py
passbird/passbird.py
passbird-1.0.0.dist-info/LICENSE
passbird-1.0.0.dist-info/METADATA
passbird-1.0.0.dist-info/WHEEL
passbird-1.0.0.dist-info/entry_points.txt
passbird-1.0.0.dist-info/top_level.txt
passbird-1.0.0.dist-info/RECORD
