Metadata-Version: 2.1
Name: passbird
Version: 1.0.0
Summary: Python Password Generator - Generate strong and secure passwords!
Home-page: https://github.com/jrt345/PassBird
Author: jrt345
License: MIT
Classifier: Environment :: Console
Classifier: Intended Audience :: End Users/Desktop
Classifier: License :: OSI Approved :: MIT License
Classifier: Operating System :: OS Independent
Classifier: Programming Language :: Python :: 3
License-File: LICENSE
Requires-Dist: click
